{"unter allen umständen":["unter allen Umständen","千万要"],"überwachen und strafen":["Überwachen und Strafen","规训与惩罚"],"und das wird genügen":["und das wird genügen","即可"],"unbemerkt eindringen":["unbemerkt eindringen","混入"],"unsinn reden":["Unsinn reden","瞎说"],"unter geheul und geschrei":["unter Geheul und Geschrei","式号式呼"],"universität passau":["Universität Passau","帕骚大学"],"uralische sprachen":["Uralische Sprachen","乌拉尔语系"],"urban vii.":["Urban VII.","乌尔巴诺七世"],"umrechnung von daten":["Umrechnung von Daten","数据转换"],"unter null":["unter Null","零下"],"unified modeling language":["Unified Modeling Language","统一建模语言"],"unverfrorener reporter":["unverfrorener Reporter","爬虫"],"ultrafeine strukturen":["ultrafeine Strukturen","超微结构"],"united nations educational":["United Nations Educational","教科文组织"],"ungekochter reis":["ungekochter Reis","米"],"untere gliedmaßen":["untere Gliedmaßen","下肢骨"],"unreife getreidekörner":["unreife Getreidekörner","粃"],"unerklärlich erscheinung":["unerklärlich Erscheinung","幽灵"],"um essen betteln":["um Essen betteln","乞食"],"um zu verhindern":["um zu verhindern","以免"],"üble laune":["üble Laune","坏脾气"],"unbewohnte insel":["unbewohnte Insel","无人岛"],"über die freundschaft":["Über die Freundschaft","交友论"],"unter zuhilfenahme von":["unter Zuhilfenahme von","借助"],"unrecht erleiden":["Unrecht erleiden","冤屈"],"unerwartetes ereignis":["unerwartetes Ereignis","意外情况"],"unverbesserlicher optimist":["unverbesserlicher Optimist","生猛"],"unglücklich elend":["unglücklich elend","晦气"],"unterricht schwänzen":["Unterricht schwänzen","逃课"],"urologische abteilung":["urologische Abteilung","泌尿科"],"unter dem knie":["unter dem Knie","膝下"],"üble praktiken":["üble Praktiken","积弊"],"um erbarmen anflehen":["um Erbarmen anflehen","乞怜"],"übernächster monat":["übernächster Monat","下下个月"],"über dem durchschnitt":["über dem Durchschnitt","高"],"übler geist":["übler Geist","祅"],"überführung in die produktion":["Überführung in die Produktion","产业化"],"um etw. zu beurteilen":["um etw. zu beurteilen","够资格评价"],"university of calgary":["University of Calgary","卡尔加里大学"],"überhitzung der konjunktur":["Überhitzung der Konjunktur","经济景气过度"],"überhitzte konjunktur":["überhitzte Konjunktur","经济景气过度"],"untere sektion":["untere Sektion","底部"],"untere teil":["untere Teil","底部"],"undeutlich handschrift":["undeutlich Handschrift","字迹模糊"],"united overseas bank":["United Overseas Bank","大华银行"],"umfassend und profund":["umfassend und profund","渊博"],"university of london":["University of London","伦敦大学"],"unbestimmtes integral":["unbestimmtes Integral","不定积分"],"über dem meeresspiegel":["über dem Meeresspiegel","海拔"],"unbeugsam vorwärts drängen":["unbeugsam vorwärts drängen","一往无前"],"unser land":["unser Land","我国"],"unser staat":["unser Staat","我们的国家"],"überwachen und kontrollieren":["überwachen und kontrollieren","监控"],"um etw. zu beweisen":["um etw. zu beweisen","为了证明"],"unfruchtbare frau":["Unfruchtbare Frau","不育夫人"],"um etw. ringen":["um etw. ringen","奋斗"],"ursache des ärger":["Ursache des Ärger","祸因"],"unterschreiben und siegeln":["unterschreiben und siegeln","签印"],"university of toronto":["University of Toronto","多伦多大学"],"unablässiges schnattern":["unablässiges Schnattern","絮语"],"ungünstige situation":["ungünstige Situation","地步"],"unsterblich werden":["unsterblich werden","成仙"],"übertrieben loben":["übertrieben loben","过奖"],"überzogene forderung":["überzogene Forderung","妄求"],"unter der zunge":["unter der Zunge","舌下"],"unbedingt einhalten":["unbedingt einhalten","必须进行"],"ungenügend vorbereitet":["ungenügend vorbereitet","准备不够"],"umso besser":["umso besser","那就更好"],"u.s. secretary of state":["U.S. Secretary of State","国务卿"],"urlaub nehmen":["Urlaub nehmen","脱产"],"überaus geduldig sein":["überaus geduldig sein","百问不烦"],"u-bahn von shanghai":["U-Bahn von Shanghai","上海轨道交通"],"unterpräfektur tokachi":["Unterpräfektur Tokachi","十胜支厅"],"um jeden preis":["um jeden Preis","不惜代价"],"university of western australia":["University of Western Australia","西澳大学"],"um etw. herumgehen":["um etw. herumgehen","踅"],"umständliche formalitäten":["umständliche Formalitäten","繁文缛节"],"unterbrechungsfreie stromversorgung":["unterbrechungsfreie Stromversorgung","不间断供电"],"unsinn erzählen":["Unsinn erzählen","胡诌"],"unschätzbar wertvoll":["unschätzbar wertvoll","价值连城"],"unter dem pantoffel stehen":["unter dem Pantoffel stehen","妻管严"],"unverschämt und vorlaut":["unverschämt und vorlaut","张狂"],"übermäßig trinken":["übermäßig trinken","醟"],"unternehmen mit auslandskapital":["Unternehmen mit Auslandskapital","外资企业"],"unglücklich sein":["unglücklich sein","心酸"],"unheilbare krankheit":["unheilbare Krankheit","绝症u"],"umweg gehen":["Umweg gehen","绕远儿"],"universität linköping":["Universität Linköping","林雪平大学"],"üppigkeit von kleidung":["Üppigkeit von Kleidung","丰衣"],"university of queensland":["University of Queensland","昆士兰大学"],"urheberrechtlich geschützt":["urheberrechtlich geschützt","正版"],"unechtes ergebnis":["unechtes Ergebnis","伪迹"],"universität newcastle":["Universität Newcastle","纽卡斯尔大学"],"überschwängliche gastfreundlichkeit":["überschwängliche Gastfreundlichkeit","盛情"],"unterdrücktes volk":["unterdrücktes Volk","被压迫民族"],"übereinstimmen mit":["übereinstimmen mit","合乎"],"umzäuntes grundstück":["umzäuntes Grundstück","院"],"um geld spielen":["um Geld spielen","赌博"],"um aussagen aufeinander abzustimmen":["um Aussagen aufeinander abzustimmen","串供"],"ungleichmäßige perle":["ungleichmäßige Perle","玑"],"ungedeckter scheck":["ungedeckter Scheck","空头支票"],"umfassender schutz":["umfassender Schutz","全面保护"],"umherschweifende banditen":["umherschweifende Banditen","流寇"],"ungefährer inhalt":["Ungefährer Inhalt","大体内容"],"universität southampton":["Universität Southampton","南安普敦大学"],"ungehobelter kerl":["ungehobelter Kerl","伧"],"ultima ratio":["ultima Ratio","最后通牒"],"um zu":["um zu","以使"],"und sogleich":["und sogleich","一看就"],"unanständige bilder oder figuren":["unanständige Bilder oder Figuren","春宫"],"unter der erde verstecken":["unter der Erde verstecken","埋藏"],"übertragung von zeitungsseiten":["Übertragung von Zeitungsseiten","报纸版面传输"],"universität aston":["Universität Aston","阿斯顿大学"],"untersuchung vor ort":["Untersuchung vor Ort","踏勘"],"um etw. zu erreichen":["um etw. zu erreichen","齐心协力"],"umfang der abnahme":["Umfang der Abnahme","跌幅"],"überflüssige wörter":["überflüssige Wörter","废话"],"university of michigan":["University of Michigan","密歇根大学"],"übermenschliche kraft":["übermenschliche Kraft","屃"],"university of waikato":["University of Waikato","怀卡托大学"],"umerziehung durch arbeit":["Umerziehung durch Arbeit","劳动教养"],"uws nuur":["Uws Nuur","乌布苏湖"],"übel riechend":["übel riechend","臭烘烘"],"um es anzuwenden":["um es anzuwenden","学以致用"],"unzüchtig und lasterhaft":["unzüchtig und lasterhaft","淫邪"],"uniform code council":["Uniform Code Council","均匀码理事会"],"unter keinen umständen":["unter keinen Umständen","千万别"],"üble absichten haben":["üble Absichten haben","包藏祸心"],"universität der vereinten nationen":["Universität der Vereinten Nationen","联合国大学"],"über jeden verdacht erhaben":["über jeden Verdacht erhaben","无可怀疑"],"ungarisches gulasch":["Ungarisches Gulasch","匈牙利式炖肉"],"unglücklicher zufall":["unglücklicher Zufall","不合适宜"],"unvollständige lähmung":["unvollständige Lähmung","轻度瘫痪"],"unendliche menge":["unendliche Menge","无限集"],"ursprüngliches bild":["ursprüngliches Bild","原图"],"utah jazz":["Utah Jazz","犹他爵士"],"universität zu lübeck":["Universität zu Lübeck","吕贝克大学"],"urheber einer sache":["Urheber einer Sache","创办人"],"unrechtmäßigen gewinn einstreichen":["unrechtmäßigen Gewinn einstreichen","渔利"],"universität dundee":["Universität Dundee","邓迪大学"],"unechte brüche":["unechte Brüche","假分数"],"uneigentliche brüche":["uneigentliche Brüche","假分数"],"unfreundliche erscheinung":["unfreundliche Erscheinung","不和悦的样子"],"unangenehmer körpergeruch":["unangenehmer Körpergeruch","狐臭"],"um gunst  flehen":["um Gunst  flehen","摇尾乞怜"],"university of sydney":["University of Sydney","悉尼大学"],"über und über":["über und über","完完全全"],"unter der flagge":["unter der Flagge","旗下"],"unwahrheiten verbreiten":["Unwahrheiten verbreiten","以讹传讹"],"umwandlung einer gewebsart":["Umwandlung einer Gewebsart","化生"],"universelle algebra":["Universelle Algebra","泛代数"],"über den tisch beugen":["über den Tisch beugen","伏案"],"unbeständige witterung":["unbeständige Witterung","不稳定天气"],"unbekannter namen":["unbekannter Namen","未命名"],"ungenügende bezahlung":["ungenügende Bezahlung","少付"],"ungekürzte buch":["ungekürzte Buch","足本"],"urusei yatsura":["Urusei Yatsura","福星小子"],"unfruchtbares ei":["unfruchtbares Ei","毈"],"ulmer münster":["Ulmer Münster","乌尔姆大教堂"],"ungerade funktion":["ungerade Funktion","奇函数"],"übler geruch":["übler Geruch","臭味"],"über etw. hinausgehen":["über etw. hinausgehen","逾越"],"um verzeihung bitten":["um Verzeihung bitten","抱歉"],"university of york":["University of York","英国约克大学"],"umzingeln und angreifen":["umzingeln und angreifen","围追堵截"],"überschreiten abgott":["überschreiten Abgott","超越偶像"],"überernährt sein":["überernährt sein","营养过剩"],"überprüfen und gutheißen":["überprüfen und gutheißen","核定"],"übereinander drucken":["übereinander drucken","套印"],"unter einem dach":["unter einem Dach","同堂"],"umfangreiches sortiment":["umfangreiches Sortiment","范围广泛"],"urlaub machen":["Urlaub machen","去度假"],"unheil erleiden":["Unheil erleiden","遭殃"],"url  schicken":["URL  schicken","发链接"],"ungenügende ladung":["ungenügende Ladung","定价过低"],"universität dortmund":["Universität Dortmund","多特蒙德大学"],"unter druck setzen":["unter Druck setzen","施压"],"unwiderlegbarer beweis":["unwiderlegbarer Beweis","铁证"],"university of melbourne":["University of Melbourne","墨尔本大学"],"united states marshals service":["United States Marshals Service","美国法警"],"überzogene werbeanstrengungen":["überzogene Werbeanstrengungen","炒作"],"unbezahlbare kostbarkeit":["unbezahlbare Kostbarkeit","无价之宝"],"unbezahlbaren schatz":["unbezahlbaren Schatz","无价之宝"],"unbezahlt freigestellt":["unbezahlt freigestellt","停薪留职"],"übrig bleiben":["übrig bleiben","残留"],"universelle url":["universelle URL","通用网址"],"universität malaya":["Universität Malaya","马来亚大学"],"university of wisconsin":["University of Wisconsin","威斯康星大学"],"unruhe stiften":["Unruhe stiften","惹事"],"united states military academy":["United States Military Academy","西点军校"],"über den preis konkurrieren":["über den Preis konkurrieren","竞价"],"unabhängige unternehmen":["unabhängige Unternehmen","独立企业"],"unauflösbarer knoten":["unauflösbarer Knoten","死结"],"überrascht sein":["überrascht sein","惊奇"],"united states forces japan":["United States Forces Japan","驻日美军"],"um die welt reisen":["um die Welt reisen","前往世界各地"],"überhaupt nicht":["überhaupt nicht","一点不"],"uesugi kagekatsu":["Uesugi Kagekatsu","上杉景胜"],"unterer bereich":["unterer Bereich","低端"],"übermittelt werden":["übermittelt werden","传来"],"unterirdischen tunnel":["unterirdischen Tunnel","地下通道"],"ungarische eiche":["Ungarische Eiche","匈牙利橡樹"],"und umgekehrt":["und umgekehrt","反之亦然"],"unter lebensgefahr":["unter Lebensgefahr","冒着生命危险"],"universelle eigenschaft":["Universelle Eigenschaft","泛性质"],"überall hohes ansehen genießen":["überall hohes Ansehen genießen","八面威风"],"unter kontrolle":["unter Kontrolle","被控制住"],"universität coimbra":["Universität Coimbra","科英布拉大学"],"unruhe in etw. bringen":["Unruhe in etw. bringen","捅马蜂窝"],"umstandshalber resignieren":["umstandshalber resignieren","苟且"],"unmittelbare staatsausgaben":["unmittelbare Staatsausgaben","直接国库开支"],"überzeugende redner":["überzeugende Redner","說客"],"unzählige kämpfe miterlebt haben":["unzählige Kämpfe miterlebt haben","身经百战"],"übriggebliebene truppen":["übriggebliebene Truppen","馀烬"],"unverheiratete frau":["unverheiratete Frau","独身女性"],"union jack":["Union Jack","英国国旗"],"unpolierter reis":["unpolierter Reis","粝"],"unter diesen umständen":["unter diesen Umständen","情况下"],"ungebräuchliches wort":["ungebräuchliches Wort","冷字"],"um ihn zu kompromittieren":["um ihn zu kompromittieren","栽赃"],"um hilfe ersuchen":["um Hilfe ersuchen","寻求救助"],"um hilfe anrufen":["um Hilfe anrufen","寻求救助"],"über eine fläche verteilen":["über eine Fläche verteilen","分布"],"unsolide und ausschweifend":["unsolide und ausschweifend","不消"],"unbeschränkte haftung":["unbeschränkte Haftung","无限责任"],"unschätzbarer wert":["unschätzbarer Wert","价值连成"],"unverständliches gebabbel":["unverständliches Gebabbel","囒"],"ungerechtfertigt anklagen":["ungerechtfertigt anklagen","囒"],"über dem boden":["über dem Boden","井上"],"unter kälte leiden":["unter Kälte leiden","挨冻"],"überheblich sein":["überheblich sein","拿大"],"ungesatteltes pferd reiten":["ungesatteltes Pferd reiten","骣"],"unser lautes heim":["Unser lautes Heim","成长的烦恼"],"um einen verstorbenen trauern":["um einen Verstorbenen trauern","伤逝"],"überheblich und geltungssüchtig":["überheblich und geltungssüchtig","逞强"],"urheberrecht verletzen":["Urheberrecht verletzen","侵犯著作权"],"unter der hand":["unter der Hand","暗暗地"],"unintelligente datenstation":["unintelligente Datenstation","哑终端"],"übermäßiger genuss":["übermäßiger Genuss","过分放纵"],"über etw. fegen":["über etw. fegen","席卷"],"unterricht erteilen":["Unterricht erteilen","授课"],"unterricht geben":["Unterricht geben","授课"],"uefa champions league":["UEFA Champions League","歐冠盃"],"united states navy":["United States Navy","美国海军"],"unbestimmter artikel":["unbestimmter Artikel","不定冠词"],"über etw. erstaunt sein":["über etw. erstaunt sein","感到惊奇"],"unelastische nachfrage":["unelastische Nachfrage","非弹性需求"],"unrechtmäßiger gewinn":["unrechtmäßiger Gewinn","油水"],"universität basel":["Universität Basel","巴塞尔大学"],"uneheliches kind":["uneheliches Kind","私孩子"],"uneinbringliche forderung":["uneinbringliche Forderung","坏账"],"universität tokio":["Universität Tokio","东京大学"],"unternehmen seelöwe":["Unternehmen Seelöwe","海狮计划"],"ultimatives ende":["ultimatives Ende","终极"],"unmittelbar nach":["unmittelbar nach","伴随"],"universität mailand":["Universität Mailand","米兰大学"],"ungewöhnliche aura":["ungewöhnliche Aura","气派不凡"],"über die ufer treten":["über die Ufer treten","横溢"],"urheber einer freveltat":["Urheber einer Freveltat","始作俑者"],"überall hin":["überall hin","天南海北"],"uraltes magisches quadrat":["uraltes magisches Quadrat","河图"],"untersuchen und fehler verbessern":["untersuchen und Fehler verbessern","勘正"],"uber cup":["Uber Cup","尤伯杯"],"unter fremden namen":["unter fremden Namen","冒名"],"üppiges wachstum":["üppiges Wachstum","芃"],"universität lund":["Universität Lund","隆德大学"],"ungefähre bedeutung":["ungefähre Bedeutung","大概的意思"],"unheimliches ereignis":["unheimliches Ereignis","不寻常的事情"],"university of virginia":["University of Virginia","弗吉尼亚大学"],"universität heidelberg":["Universität Heidelberg","海德堡大学"],"übler scherz":["übler Scherz","恶作剧"],"unlizensierter betrieb":["unlizensierter Betrieb","无照经营"],"unlizensiertes wirtschaften":["unlizensiertes Wirtschaften","无照经营"],"unangenehm grell":["unangenehm grell","贼亮"],"unsere bildungseinrichtung":["unsere Bildungseinrichtung","本校"],"umziehen nach":["umziehen nach","迁移"],"überfordert sein":["überfordert sein","绠短汲深"],"ungesunde tendenz":["ungesunde Tendenz","歪风"],"unterschiedliche grade":["unterschiedliche Grade","程度不同"],"und so weiter":["und so weiter","什么的"],"ungezogener mensch":["ungezogener Mensch","无教养的人"],"um etw. herum":["um etw. herum","围绕着"],"umso mehr":["umso mehr","愈加"],"um sein leben kämpfen":["um sein Leben kämpfen","挣命"],"ungekämmt und ungewaschen":["ungekämmt und ungewaschen","蓬头垢面"],"unter null grad":["unter Null Grad","零下"],"unschön zu hören":["unschön zu hören","不悦耳"],"university of pittsburgh":["University of Pittsburgh","匹兹堡大学"],"unerreichbares erstreben":["Unerreichbares erstreben","海底捞月"],"überhaupt nicht berücksichtigen":["überhaupt nicht berücksichtigen","无视"],"ultima online":["Ultima Online","网络创世纪"],"umfassendes projektmanagement":["umfassendes Projektmanagement","全面项目管理"],"u-bahn station":["U-Bahn Station","地铁车站"],"u-bahn haltestelle":["U-Bahn Haltestelle","地铁车站"],"united airlines":["United Airlines","联合航空"],"umberto i.":["Umberto I.","翁贝托一世"],"unzertrennbar verbunden":["unzertrennbar verbunden","密不可分"],"überarbeiteter arbeiter":["überarbeiteter Arbeiter","过劳模"],"übernächste woche":["übernächste Woche","下下个星期"],"über etw. hinwegkommen":["über etw. hinwegkommen","越过"],"unsere heimat":["unsere Heimat","我国"],"über etw. hinüber klettern":["über etw. hinüber klettern","翻过"],"uriah heep":["Uriah Heep","尤拉希普"],"unter nennwert":["unter Nennwert","低于正常价格"],"unter dem normalpreis":["unter dem Normalpreis","低于正常价格"],"um beurlaubung bitten":["um Beurlaubung bitten","告假"],"umerziehung  durch körperliche arbeit":["Umerziehung  durch körperliche Arbeit","劳动改造"],"unerwartete freude":["unerwartete Freude","喜出望外"],"unreife heuschrecken":["unreife Heuschrecken","蝻"],"ukita hideie":["Ukita Hideie","宇喜多秀家"],"umgekehrte psychologie":["umgekehrte Psychologie","反向心理"],"university of waterloo":["University of Waterloo","滑铁卢大学"],"us-sowjetische beziehungen":["US-Sowjetische Beziehungen","美苏关系"],"um einen weiteren schritt":["um einen weiteren Schritt","进一步"],"unbeteiligter beobachter":["unbeteiligter Beobachter","吃瓜群众"],"überprüfung  der funktionäre":["Überprüfung  der Funktionäre","干部的考察"],"unter anderem namen":["unter anderem Namen","化名"],"unbemanntes flugzeug":["unbemanntes Flugzeug","无人驾驶飞机"],"unregelmäßiger herzschlag":["unregelmäßiger Herzschlag","心律不齐"],"unbedingt sollen":["unbedingt sollen","务要"],"unterdrückt werden":["unterdrückt werden","受压迫"],"über etw. meckern":["über etw. meckern","挑剔"],"überstürzte hamsterkäufe":["überstürzte Hamsterkäufe","抢购风潮"],"ungerechtfertigte bereicherung":["ungerechtfertigte Bereicherung","不当得利"],"umher reisen":["umher reisen","游弋"],"umher kreuzen":["umher kreuzen","游弋"],"über allem stehen":["über allem stehen","清高"],"über alles erhaben sein":["über alles erhaben sein","清高"],"us airways":["US Airways","全美航空"],"üppig wachsen":["üppig wachsen","蓁蓁"],"unveräußerliches gut":["unveräußerliches Gut","自然权利"],"um anweisung ersuchen":["um Anweisung ersuchen","请示"],"untrennbarer zusammenhang":["untrennbarer Zusammenhang","关系密不可分"],"überschlag machen":["Überschlag machen","翻筋斗"],"um antwort wird gebeten":["um Antwort wird gebeten","敬请回复"],"u.s. dollar index":["U.S. Dollar Index","美元指数"],"under control":["Under Control","玻璃樽"],"unter aller kritik":["unter aller Kritik","不值一提"],"ungarischer flieder":["Ungarischer Flieder","匈牙利丁香"],"unterjochte nation":["unterjochte Nation","亡国"],"umbenannt werden in":["umbenannt werden in","将改名"],"u-bahn seoul":["U-Bahn Seoul","首尔地铁"],"unglaublich große":["unglaublich große","空前"],"united malays national organisation":["United Malays National Organisation","巫统"],"unendlich wolkenloser himmel":["unendlich wolkenloser Himmel","晴空万里"],"unter vier augen":["unter vier Augen","私底下"],"ursprüngliche heimat":["ursprüngliche Heimat","祖籍"],"unerwartet schlecht":["unerwartet schlecht","不如人意的"],"university of florida":["University of Florida","佛罗里达大学"],"universität kassel":["Universität Kassel","卡塞尔大学"],"university of oregon":["University of Oregon","俄勒冈大学"],"überflüssig zu erwähnen":["überflüssig zu erwähnen","别提"],"üppig blühen":["üppig blühen","郁郁葱葱"],"üble nachrede":["üble Nachrede","有损名誉"],"unter freiem himmel":["unter freiem Himmel","在露天"],"um aufgezählt zu werden":["um aufgezählt zu werden","罄竹难书"],"undeutlich machen":["undeutlich machen","混淆"],"überfallen werden":["überfallen werden","持械抢劫"],"u-bahn pjöngjang":["U-Bahn Pjöngjang","平壤地铁"],"um stimmen werben":["um Stimmen werben","助选"],"universität duisburg":["Universität Duisburg","杜伊斯堡大学"],"unsicher sein":["unsicher sein","拿不准"],"unverhofftes glück":["unverhofftes Glück","意外的好运气"],"unüberwindlich sein":["unüberwindlich sein","不能克服"],"übergeschnappt sein":["übergeschnappt sein","发疯"],"uterus myomatosus":["Uterus myomatosus","子宫肌瘤"],"über etw. verfügen":["über etw. verfügen","领有"],"ueto aya":["Ueto Aya","上户彩"],"übermäßig regieren":["übermäßig regieren","反应过度"],"university of liverpool":["University of Liverpool","利物浦大学"],"untergeordnet sein":["untergeordnet sein","隶"],"university of southern california":["University of Southern California","南加州大学"],"um hilfe rufen":["um Hilfe rufen","呼救"],"umstellung auf elektrotraktion":["Umstellung auf Elektrotraktion","电气化改造"],"und noch mehr":["und noch mehr","一发"],"üble angewohnheit":["üble Angewohnheit","习气"],"über dem erdboden liegend":["über dem Erdboden liegend","地上"],"um etw. zu sehen":["um etw. zu sehen","引颈而望"],"unmögliches ereignis":["unmögliches Ereignis","不可能事件"],"um die ecke biegen":["um die Ecke biegen","拐弯儿"],"ungefüttertes gewand":["ungefüttertes Gewand","衫"],"unter bewachung":["unter Bewachung","被押"],"unattraktive frau":["unattraktive Frau","獢"],"ungebranntes werkstück":["ungebranntes Werkstück","胎"],"urbar machen":["urbar machen","农垦"],"urbane gesellschaft":["urbane Gesellschaft","城镇社会"],"überfall auf offener strecke":["Überfall auf offener Strecke","路霸"],"ungesetzlicher handel":["ungesetzlicher Handel","非法贩卖"],"unnütz sein":["unnütz sein","没有用处"],"unendliche reihe":["unendliche Reihe","无穷级数"],"unter beweis gestellt":["unter Beweis gestellt","证明是"],"university of iowa":["University of Iowa","爱荷华大学"],"unter dem mond":["unter dem Mond","月下"],"und vice versa":["und vice versa","亦"],"um sein leben schreien":["um sein Leben schreien","拼命喊"],"unter dem vulkan":["Unter dem Vulkan","火山下"],"über die landesgrenzen hinaus":["über die Landesgrenzen hinaus","超越国界"],"übertragene bedeutung":["übertragene Bedeutung","转义"],"überblick geben":["Überblick geben","概论"],"unverständlich reden":["unverständlich reden","东拉西扯"],"unbedingt müssen":["unbedingt müssen","不能不"],"über jahre hinweg totenstill":["über Jahre hinweg totenstill","沉寂多年"],"union pay bank card":["Union Pay Bank Card","银联卡"],"unmögliches verlangen":["unmögliches Verlangen","赶鸭子上架"],"universität osaka":["Universität Osaka","大阪大学"],"unbedacht handeln":["unbedacht handeln","妄为"],"unbesonnen agieren":["unbesonnen agieren","妄为"],"udmurtische sprache":["Udmurtische Sprache","乌德穆尔特语"],"universität stuttgart":["Universität Stuttgart","斯图加特大学"],"übertragen werden an":["übertragen werden an","转由"],"unterricht am krankenbett":["Unterricht am Krankenbett","临床教学"],"ungelöst bleiben":["ungelöst bleiben","不了了之"],"um die wette saufen":["um die Wette saufen","拼酒"],"universität edinburgh":["Universität Edinburgh","爱丁堡大学"],"unabhängiges königreich":["unabhängiges Königreich","独立王国"],"us-amerikanische küche":["US-amerikanische Küche","美国烹饪"],"umgebung ohne sauerstoff":["Umgebung ohne Sauerstoff","无氧"],"um die brust herum":["um die Brust herum","乳房上"],"university of wisconsin system":["University of Wisconsin System","威斯康辛大学"],"um kindersegen zu erwirken":["um Kindersegen zu erwirken","拴娃娃"],"u-bahn tokio":["U-Bahn Tokio","东京地下铁"],"übung macht den meister":["Übung macht den Meister","熟能生巧"],"universität oxford":["Universität Oxford","牛津大学"],"uhrzeit und datum":["Uhrzeit und Datum","时日"],"unter einer decke stecken":["unter einer Decke stecken","狼狈为奸"],"uhr mit glockenspiel":["Uhr mit Glockenspiel","自鸣钟"],"untersuchen und darauf aufpassen":["untersuchen und darauf aufpassen","查处"],"unermeßlich mächtig":["unermeßlich mächtig","浩荡"],"unaufrichtige ideen":["unaufrichtige Ideen","歪主意"],"universität auckland":["Universität Auckland","奥克兰大学"],"unrechtmäßig erlangen":["unrechtmäßig erlangen","兜"],"unter der hilfe von":["unter der Hilfe von","在帮助下"],"über zehn jahre":["über zehn Jahre","十多年"],"überbetonung der handelsseite":["Überbetonung der Handelsseite","商业炒作"],"unüberlegt sprechen":["unüberlegt sprechen","乱说"],"unverantwortliche bemerkungen machen":["unverantwortliche Bemerkungen machen","乱说"],"universität wien":["Universität Wien","维也纳大学"],"unbestimmte wärmeeinheit":["unbestimmte Wärmeeinheit","克卡"],"user agent":["User Agent","使用者中介"],"ungarische sprache":["Ungarische Sprache","匈牙利语"],"ursprünglicher name":["ursprünglicher Name","原名"],"umarmungen und küsse":["Umarmungen und Küsse","么么哒"],"unregelmäßiger knochen":["unregelmäßiger Knochen","不规则骨"],"überzogenes konto":["überzogenes Konto","透支账户"],"universität ulm":["Universität Ulm","乌尔姆大学"],"university of minnesota system":["University of Minnesota System","明尼苏达大学"],"unterirdischer wasserverlauf":["unterirdischer Wasserverlauf","巠"],"unmittelbar unterstehend":["unmittelbar unterstehend","直属"],"unmittelbar unterstellt":["unmittelbar unterstellt","直属"],"über die jahre":["über die Jahre","经年累月"],"unverzollte ware":["unverzollte Ware","水货"],"ungestrichenes papier":["ungestrichenes Papier","非涂料纸"],"university of surrey":["University of Surrey","萨里大学"],"ulster university":["Ulster University","阿尔斯特大学"],"üppige vegetation":["üppige Vegetation","蓊"],"us-amerikanischer film":["US-amerikanischer Film","美国电影"],"unzählige leiden":["unzählige Leiden","千辛万苦"],"untrennbar eng":["untrennbar eng","紧密"],"übersehenes gebiet":["übersehenes Gebiet","盲区"],"umherwandernde vagabunden":["umherwandernde Vagabunden","盲流"],"us-invasion in panama":["US-Invasion in Panama","入侵巴拿马"],"untere niveau":["untere Niveau","低标准"],"urban vi.":["Urban VI.","乌尔巴诺六世"],"überlegen sein":["überlegen sein","胜似"],"überrascht werden":["überrascht werden","吃惊"],"unter einsatz seines lebens":["unter Einsatz seines Lebens","出生入死"],"unerwartete katastrophe":["unerwartete Katastrophe","横祸"],"unerwartetes unglück":["unerwartetes Unglück","横祸"],"unerwünschte werbe-e-mail":["unerwünschte Werbe-E-Mail","垃圾邮件"],"unabgesprochen das gleiche tun":["unabgesprochen das gleiche tun","不约而同"],"über nacht":["über Nacht","通宵"],"university of rochester":["University of Rochester","罗彻斯特大学"],"us-amerikanische nationalhymne":["US-amerikanische Nationalhymne","美国国歌"],"unterschiedliche zeitleiste":["unterschiedliche Zeitleiste","时间不同"],"überhaupt nicht schlecht":["überhaupt nicht schlecht","蛮不错"],"universität von otago":["Universität von Otago","奥塔哥大学"],"ugaritische schrift":["Ugaritische Schrift","乌加里特字母"],"univariate funktion":["univariate Funktion","一元函数"],"untere trias":["untere Trias","早三叠世"],"und dergleichen":["und dergleichen","什么的"],"ursprüngliche staatsangehörigkeit":["ursprüngliche Staatsangehörigkeit","原国籍"],"um sich zusammenzuschließen":["um sich zusammenzuschließen","串联"],"über briefe miteinander kommunizieren":["über Briefe miteinander kommunizieren","通信"],"unterirdischer atomtest":["unterirdischer Atomtest","地下核试"],"überschweres wasser":["überschweres Wasser","氚化水"],"ungestempeltes schwein":["ungestempeltes Schwein","白条猪"],"überstunden machen":["Überstunden machen","加班"],"university of buckingham":["University of Buckingham","白金汉大学"],"unterwäsche für frauen":["Unterwäsche für Frauen","衵"],"überall sehr bekannt":["überall sehr bekannt","家喻户晓"],"üppiges grün":["üppiges Grün","绿油油"],"über und über grün":["über und über grün","绿油油"],"um etw. zu tun":["um etw. zu tun","来"],"üppiges blumenwachstum":["üppiges Blumenwachstum","薾"],"universitäten und hochschulen":["Universitäten und Hochschulen","大专院校"],"ufida software co.ltd":["UFIDA Software CO.LTD","用友集团"],"unter jeder kritik":["unter jeder Kritik","不值识者一笑"],"united daily news":["United Daily News","联合报"],"uesugi kenshin":["Uesugi Kenshin","上杉谦信"],"unerwartet eintreten":["unerwartet eintreten","突发"],"unter dem einfluss":["unter dem Einfluss","受作用"],"überall gewesen sein":["überall gewesen sein","走遍天涯"],"umerziehung durch zwangsarbeit":["Umerziehung durch Zwangsarbeit","劳改"],"über den winter kommen":["über den Winter kommen","过冬"],"um die meinung fragen":["um die Meinung fragen","征求意见"],"unabhängige variable":["unabhängige Variable","自变数"],"urkaiser chinas":["Urkaiser Chinas","三皇五帝"],"über jahre hinweg":["über Jahre hinweg","连年"],"universelle werkzeugfräsmaschine":["Universelle Werkzeugfräsmaschine","万能工具铣床"],"über jmdn. herfallen":["über jmdn. herfallen","搏"],"unkraut jäten":["Unkraut jäten","拔杂草"],"unbewegliches pferd":["unbewegliches Pferd","騺"],"übervorsichtig und unentschlossen":["übervorsichtig und unentschlossen","畏首畏尾"],"um jemanden zu verurteilen":["um jemanden zu verurteilen","群起而攻之"],"über wasser":["über Wasser","在海上"],"übler gedanke":["übler Gedanke","邪念"],"ungelernte arbeitskraft":["ungelernte Arbeitskraft","杂工"],"unbekanntes flugobjekt":["Unbekanntes Flugobjekt","幽浮"],"universitäre selbstverwaltung":["universitäre Selbstverwaltung","大学自治"],"unaufhaltsame strömung":["unaufhaltsame Strömung","汹涌澎湃"],"unerträglich sein":["unerträglich sein","耐"],"ursprüngliche form":["ursprüngliche Form","原样"],"umgekehrte reihenfolge":["umgekehrte Reihenfolge","倒序"],"unangenehm sein":["unangenehm sein","嗍"],"über etw. hinaus":["über etw. hinaus","超乎"],"universität gifu":["Universität Gifu","岐阜大学"],"über uns":["über uns","关于我们"],"übermäßig heilmittel einnehmen":["übermäßig Heilmittel einnehmen","恶补"],"übermäßig medikamente einnehmen":["übermäßig Medikamente einnehmen","恶补"],"unschuldige spielgefährten sein":["unschuldige Spielgefährten sein","两小无猜"],"united states forces korea":["United States Forces Korea","驻韩美军"],"übertrieben kritisch sein":["übertrieben kritisch sein","评头品足"],"überall verbreitet":["überall verbreitet","遍布"],"unwissende person":["unwissende Person","白丁"],"undeutlich sprechen":["undeutlich sprechen","呫"],"unterdrückte gefühle":["unterdrückte Gefühle","憋在心里"],"überschwänglich entzückt sein":["überschwänglich entzückt sein","眉飞色舞"],"universität hasselt":["Universität Hasselt","哈塞尔特大学"],"united states army":["United States Army","美国陆军"],"übers ganze gesicht lächeln":["übers ganze Gesicht lächeln","满面笑容"],"unterlegen sein":["unterlegen sein","劣势"],"unbemanntes kampfflugzeug":["Unbemanntes Kampfflugzeug","无人战机"],"universität leiden":["Universität Leiden","莱顿大学"],"ungeschlechtliche fortpflanzung":["ungeschlechtliche Fortpflanzung","无性生殖"],"unabhängiger staat":["unabhängiger Staat","独立国家"],"ungerade zahl":["ungerade Zahl","奇数"],"unreife bohnen":["unreife Bohnen","豏"],"überarbeitete  ausgabe":["überarbeitete  Ausgabe","修订本"],"unvollständige  im internet":["unvollständige  im Internet","太监贴"],"unsichtbare klippe":["unsichtbare Klippe","暗礁"],"ungesättigte fette":["ungesättigte Fette","偷着胖"],"university of adelaide":["University of Adelaide","阿德莱德大学"],"unaufrichtig sprechen":["unaufrichtig sprechen","言不由衷"],"unbewaffnetes auge":["unbewaffnetes Auge","肉眼"],"universität leipzig":["Universität Leipzig","莱比锡大学"],"undurchdringliches netz":["undurchdringliches Netz","天罗地网"],"über dem nennwert":["über dem Nennwert","高于票面价值"],"university of nairobi":["University of Nairobi","内罗毕大学"],"unbefugte nutzung":["unbefugte Nutzung","非法盗用"],"unterschwelliger einfluss":["unterschwelliger Einfluss","潜移默化"],"us-amerikanische recht":["US-Amerikanische Recht","美国法律"],"unbewegliche habe":["unbewegliche Habe","产业"],"unendlich fröhlich":["unendlich fröhlich","其乐无穷"],"universität hamburg":["Universität Hamburg","汉堡大学"],"unsichtbare barriere":["unsichtbare Barriere","玻璃天花板"],"unkompliziertes handling":["unkompliziertes Handling","操作简便"],"unkonventionelle jugendliche":["unkonventionelle Jugendliche","古惑仔"],"unrechtmäßig besitz ergreifen":["unrechtmäßig Besitz ergreifen","霸占"],"um geld betteln":["um Geld betteln","告饶"],"ungestempelter vertrag":["ungestempelter Vertrag","白契"],"unter hoher druck stehen":["unter hoher Druck stehen","负担重"],"unabängigkeit tibets":["Unabängigkeit Tibets","西藏独立"],"ungesäuerter teig":["Ungesäuerter Teig","死面"],"und sogar":["und sogar","乃至"],"unter den hammer bringen":["unter den Hammer bringen","拍卖"],"unvorhergesehenes ereignis":["unvorhergesehenes Ereignis","不测"],"um zehn ecken herum":["um zehn Ecken herum","转弯抹角"],"unsagbar schön":["unsagbar schön","妙不可言"],"urban viii.":["Urban VIII.","乌尔巴诺八世"],"uncanny valley":["Uncanny Valley","恐怖谷理论"],"übrig lassen":["übrig lassen","走掉"],"urheber einer aktion":["Urheber einer Aktion","发动者"],"uneingelöste pfandstücke verkaufen":["uneingelöste Pfandstücke verkaufen","打当"],"umfassendes reformpaket":["umfassendes Reformpaket","综合配套改革"],"um eigene mängel auszugleichen":["um eigene Mängel auszugleichen","取长补短"],"um den preis feilschen":["um den Preis feilschen","还价"],"um eine kleinigkeit bitten":["um eine Kleinigkeit bitten","寻"],"ubon ratana":["Ubon Ratana","乌汶叻公主"],"unabhängigkeitsbewegung taiwans":["Unabhängigkeitsbewegung Taiwans","台湾独立运动"],"unerwünschter dritter gast":["unerwünschter dritter Gast","电灯泡"],"unter zeitdruck":["unter Zeitdruck","仓促"],"unruhen in usbekistan":["Unruhen in Usbekistan","安集延事件"],"um aufzustehen":["um aufzustehen","赖床"],"ungemein flink":["ungemein flink","神速"],"unregelmäßiges verb":["unregelmäßiges Verb","不规则动词"],"umfang zirkel":["Umfang Zirkel","周"],"unterirdische wasserleitung":["unterirdische Wasserleitung","涵洞"],"über feinheiten nachdenken":["über Feinheiten nachdenken","玩味"],"unterschlagenes oder gestohlenes geld":["unterschlagenes oder gestohlenes Geld","赃款"],"unbedingter programmsatz":["unbedingter Programmsatz","命令句"],"über etw. wachen":["über etw. wachen","守护"],"universität konstanz":["Universität Konstanz","康斯坦茨大学"],"unabhängigkeitserklärung der usa":["Unabhängigkeitserklärung der USA","美国独立宣言"],"unschuldig sein":["unschuldig sein","无罪"],"uwe seeler":["Uwe Seeler","乌韦泽勒"],"unten am gebäude":["unten am Gebäude","楼下"],"unten am haus":["unten am Haus","楼下"],"über achtzig":["über achtzig","八十多岁"],"unten links":["unten links","左下角"],"über einen preis verhandeln":["über einen Preis verhandeln","议价"],"universiteit utrecht":["Universiteit Utrecht","乌特勒支大学"],"unerhört hart":["unerhört hart","艰苦卓越"],"united states naval academy":["United States Naval Academy","美国海军学院"],"unregelmäßiges dreieck":["unregelmäßiges Dreieck","不等边三角形"],"ungeheuer von loch ness":["Ungeheuer von Loch Ness","尼斯湖水怪"],"umweltfreundlicher beutel":["umweltfreundlicher Beutel","环保袋"],"unruhen auslösen":["Unruhen auslösen","罗唣"],"ungebrannter lehmziegel":["ungebrannter Lehmziegel","土坯"],"unterirdische bauten":["unterirdische Bauten","地下工程"],"unverlangtes angebot":["unverlangtes Angebot","主动报价"],"urawa red diamonds":["Urawa Red Diamonds","浦和红钻"],"umsonst gewesen sein":["umsonst gewesen sein","付诸流水"],"über gewaltige stärke verfügen":["über gewaltige Stärke verfügen","实力雄厚"],"überaus leistungsfähig":["überaus leistungsfähig","实力雄厚"],"um sein leben fliehen":["um sein Leben fliehen","逃生"],"u.s. bank tower":["U.S. Bank Tower","联邦银行大厦"],"unbeschnittenes format":["unbeschnittenes Format","未裁切的尺寸"],"unterricht vorbereiten":["Unterricht vorbereiten","预习"],"urteil beibehalten":["Urteil beibehalten","维持原判"],"und doch":["und doch","而又"],"urin aufnehmen":["Urin aufnehmen","吸收尿"],"united technologies corporation":["United Technologies Corporation","联合技术公司"],"unternehmensform als aktiengesellschaft":["Unternehmensform als Aktiengesellschaft","股份制"],"überstürzt flüchten":["überstürzt flüchten","逃窜"],"über dem horizont":["über dem Horizont","在地平线上"],"unteren gliedmaßen":["unteren Gliedmaßen","下肢"],"über das wetter reden":["über das Wetter reden","叙寒温"],"über etw. murren":["über etw. murren","埋怨"],"ungeachtet dessen":["ungeachtet dessen","尽管这样"],"um etw. besorgt sein":["um etw. besorgt sein","挂虑"],"übliche gepflogenheiten":["übliche Gepflogenheiten","普遍的惯例"],"überschüssige waren":["überschüssige Waren","商品过剩"],"überfüllt sein":["überfüllt sein","込"],"ungelenkte raketenwerfer":["ungelenkte Raketenwerfer","多管火箭炮"],"und auch":["und auch","以"],"ursprüngliche akkumulation":["ursprüngliche Akkumulation","原始积累"],"unabhängiger staat samoa":["Unabhängiger Staat Samoa","萨摩亚独立国"],"unüberschaubare  folgen haben":["unüberschaubare  Folgen haben","贻害无穷"],"unechter schwertwal":["Unechter Schwertwal","伪虎鲸"],"unter wasser gesetzte felder":["unter Wasser gesetzte Felder","水亩"],"upper west side":["Upper West Side","上西城"],"umsonst gelebt":["umsonst gelebt","白活"],"ungültig gedrucktes blatt":["ungültig gedrucktes Blatt","作废印张"],"umfassende beratung":["umfassende Beratung","全面咨询指导"],"ursprung eines flusses":["Ursprung eines Flusses","源"],"universität essex":["Universität Essex","艾塞克斯大学"],"udo lindenberg":["Udo Lindenberg","乌多林登贝格"],"unerlaubt zusammenarbeiten":["unerlaubt zusammenarbeiten","勾结"],"unbefestigter feldweg":["unbefestigter Feldweg","土路"],"universität xiamen":["Universität Xiamen","厦门大学"],"unendlich weit":["unendlich weit","茫茫"],"ulrich zwingli":["Ulrich Zwingli","慈运理"],"übungsplatz für golf":["Übungsplatz für Golf","高尔夫练习场"],"user story":["User Story","用户故事"],"universität von malawi":["Universität von Malawi","马拉维大学"],"unkultiviertes land":["unkultiviertes Land","荒"],"unterstufe der oberschule":["Unterstufe der Oberschule","初中"],"ursa minor":["Ursa Minor","小熊座"],"ukrainische sprache":["ukrainische Sprache","乌克兰语"],"unmissverständliche reaktion":["unmissverständliche Reaktion","强烈反应"],"um die wette laufen":["um die Wette laufen","赛跑"],"um die wette rennen":["um die Wette rennen","赛跑"],"übers meer daher kommen":["übers Meer daher kommen","漂洋过海"],"ungehorsam sein":["ungehorsam sein","蘁"],"ursprünglicher wille":["ursprünglicher Wille","原意"],"u-boot abwehr":["U-Boot Abwehr","反潜作战"],"unzertrennlich sein":["unzertrennlich sein","鱼水情"],"umgehend reagieren":["umgehend reagieren","闻风而动"],"unter der sonne":["unter der Sonne","天底下"],"um jmds. meinung fragen":["um jmds. Meinung fragen","领教"],"um jmds. rat fragen":["um jmds. Rat fragen","领教"],"ultra density optical":["Ultra Density Optical","超密度光碟"],"ursprüngliches aussehen":["ursprüngliches Aussehen","原貌"],"überproduktion einlagern":["Überproduktion einlagern","超储"],"unerwünschte reaktion":["unerwünschte Reaktion","不良反应"],"überall im lande vorkommen":["überall im Lande vorkommen","遍布全国"],"unglück haben":["Unglück haben","背时"],"unter fließendem wasser":["unter fließendem Wasser","在水流中"],"unter gewaltanwendung":["unter Gewaltanwendung","威"],"university of leeds":["University of Leeds","利兹大学"],"unfruchtbarer boden":["unfruchtbarer Boden","白地"],"umfassende maßnahmen":["umfassende Maßnahmen","综合治理"],"übel sein":["übel sein","恶心"],"unwohl sein":["unwohl sein","恶心"],"university of hull":["University of Hull","赫尔大学"],"ums leben kommen":["ums Leben kommen","丧生"],"umständlich sein":["umständlich sein","方脑袋"],"unbeständig in seinen liebhabereien":["unbeständig in seinen Liebhabereien","喜新厌旧"],"unbesetzte position":["unbesetzte Position","缺位"],"unternehmerischer gewinn":["unternehmerischer Gewinn","经营利润"],"unter .... studieren":["unter .... studieren","受业"],"unüberlegt handeln":["unüberlegt handeln","盲人瞎马"],"unter dieser bedingung":["unter dieser Bedingung","在这种状况下"],"unbenanntes symbol":["unbenanntes Symbol","抽象符号"],"unbenanntes zeichen":["unbenanntes Zeichen","抽象符号"],"union myanmar":["Union Myanmar","缅甸联邦"],"um gnade flehen":["um Gnade flehen","求饶"],"übernatürliche dinge":["übernatürliche Dinge","超自然的事"],"um rat fragen":["um Rat fragen","讨教"],"überwiesener betrag":["überwiesener Betrag","汇付"],"unfairer spieler":["unfairer Spieler","犯规者"],"unbeirrt auf etw. bestehen":["unbeirrt auf etw. bestehen","认定"],"um kritik zu entgehen":["um Kritik zu entgehen","讳疾忌医"],"unabhängige kirchen in china":["Unabhängige Kirchen in China","中国自立教会"],"university of massachusetts":["University of Massachusetts","马萨诸塞大学"],"untere grenze":["untere Grenze","下确界"],"untere schranke":["untere Schranke","下确界"],"united kingdom":["United Kingdom","英联合王国"],"unternehmen zitadelle":["Unternehmen Zitadelle","库尔斯克会战"],"um hilfe bitten":["um Hilfe bitten","伸手"],"übertragung von druckvorlagen":["Übertragung von Druckvorlagen","印刷原稿传输"],"universität glasgow":["Universität Glasgow","格拉斯哥大学"],"unsere zeitschrift":["unsere Zeitschrift","本刊"],"um ... zu":["um ... zu","以便"],"unabhängigkeit taiwans":["Unabhängigkeit Taiwans","台独"],"unterirdisches rohr":["unterirdisches Rohr","暗管"],"unruhe anzetteln":["Unruhe anzetteln","煽风点火"],"universelle maschine":["universelle Maschine","通用机器"],"unangenehme nachrichten unterschlagen":["unangenehme Nachrichten unterschlagen","报喜不报忧"],"unfiltrierter wein":["unfiltrierter Wein","醾"],"unter der bevölkerung bekannt":["unter der Bevölkerung bekannt","民间"],"um ... willen":["um ... willen","起见"],"überhöhter luftdruck":["überhöhter Luftdruck","过分膨胀"],"ungeöffnet blume":["ungeöffnet Blume","骨朵儿"],"umweltfreundliche technologie":["umweltfreundliche Technologie","无害技术"],"unter vorbehalt":["unter Vorbehalt","附带条件"],"united kingdom independence party":["United Kingdom Independence Party","英国独立党"],"unternehmerische ressourcen":["Unternehmerische Ressourcen","企业资源"],"unglaublich genaue voraussage":["unglaublich genaue Voraussage","神算"],"unpolierter edelstein":["unpolierter Edelstein","璞"],"unter schlaflosigkeit leiden":["unter Schlaflosigkeit leiden","失眠"],"ulan bator":["Ulan Bator","乌兰巴托"],"unbesiegbare position":["unbesiegbare Position","不败之地"],"universalität des widerspruchs":["Universalität des Widerspruchs","矛盾的普遍性"],"unternehmen als juristische person":["Unternehmen als juristische Person","企业法人"],"ungünstige umstände":["ungünstige Umstände","不利因素"],"über das normale hinausgehend":["über das Normale hinausgehend","超凡"],"überschwemmung und dürre":["Überschwemmung und Dürre","水旱"],"unabhängige ereignisse":["unabhängige Ereignisse","独立事件"],"uija of baekje":["Uija of Baekje","百济义慈王"],"umklammert halten":["umklammert halten","搲"],"umgebung der hauptstadt":["Umgebung der Hauptstadt","畿"],"über nacht erfolg haben":["über Nacht Erfolg haben","蹿红"],"unterhaltsam sein":["unterhaltsam sein","好玩"],"über jmdn. bitter spotten":["über jmdn. bitter spotten","奚落"],"university of arizona":["University of Arizona","亚利桑那大学"],"ungerechte verteilung":["ungerechte Verteilung","分配不公"],"übermäßig stark ansteigen":["übermäßig stark ansteigen","狂涨"],"umverteilung überflüssiger belegschaft":["Umverteilung überflüssiger Belegschaft","分流"],"überschwerer wasserstoff":["überschwerer Wasserstoff","超重氫"],"um etw. herum drehen":["um etw. herum drehen","围绕"],"univariates polynom":["univariates Polynom","一元多项式"],"umher streifen":["umher streifen","漫游"],"umher ziehen":["umher ziehen","漫游"],"unten rechts":["unten rechts","右下角"],"unteren rechten ecke":["unteren rechten Ecke","右下角"],"unbemerkt bleiben":["unbemerkt bleiben","无声无息"],"übertragene gesetzgebung":["übertragene Gesetzgebung","委任立法"],"überall ficken":["überall ficken","到处操"],"unvergleichbares werk":["unvergleichbares Werk","霸业"],"university of california":["University of California","尔湾加州大学"],"über zehn tage":["über zehn Tage","旬外"],"ursprüngliche preisforderung":["ursprüngliche Preisforderung","讨价"],"üppigkeit von nahrung":["Üppigkeit von Nahrung","足食"],"umm al-qaiwain":["Umm al-Qaiwain","欧姆古温"],"university of utah":["University of Utah","犹他大学"],"unbeteiligte festnehmen":["Unbeteiligte festnehmen","滥捕"],"über die straße":["über die Straße","由陆路"],"unbeirrbare entschlossenheit geloben":["unbeirrbare Entschlossenheit geloben","矢志不渝"],"unebener flug eines vogels":["unebener Flug eines Vogels","翪"],"universität fuzhou":["Universität Fuzhou","福州大学"],"unentschieden spielen":["unentschieden spielen","打平"],"unerwünschte person":["unerwünschte Person","不受欢迎人物"],"üble gedanken":["üble Gedanken","慝"],"ulla schmidt":["Ulla Schmidt","乌拉施密特"],"untergeben sein":["untergeben sein","隶"],"unterfamilie grubenottern":["Unterfamilie Grubenottern","蝮蛇亚科"],"überflutete äcker dränieren":["überflutete Äcker dränieren","排涝"],"unredliche tätigkeit":["unredliche Tätigkeit","勾当"],"uns selbst":["uns selbst","我们自己"],"umbaute fläche":["umbaute Fläche","建筑面积"],"übernächstes jahr":["übernächstes Jahr","后年"],"umwerfend schön":["umwerfend schön","倾城倾国"],"udai hussein":["Udai Hussein","乌代侯赛因"],"uwe barschel":["Uwe Barschel","乌韦巴舍尔"],"ungezügelte kraft":["ungezügelte Kraft","恶浪"],"ulsan hyundai horang-i":["Ulsan Hyundai Horang-i","蔚山现代"],"überqueren der grenze":["überqueren der Grenze","过境"],"unterbrechungen des handels":["Unterbrechungen des Handels","买卖中断"],"ungeschützter sex":["ungeschützter Sex","不安全性行为"],"university of kentucky":["University of Kentucky","肯塔基大学"],"ubiquitous computing":["Ubiquitous Computing","普适计算"],"u-boot manöver":["U-Boot Manöver","疯狂伊凡"],"unsichere lage":["unsichere Lage","不稳定的局面"],"umfangreicher plan":["umfangreicher Plan","鸿图"],"university of alberta":["University of Alberta","阿尔伯塔大学"],"uncle sam":["Uncle Sam","山姆大叔"],"unmittelbare blutsverwandte":["unmittelbare Blutsverwandte","直系血亲"],"ungefütterte kleidung":["ungefütterte Kleidung","袗"],"über die rechtsprechung verfügen":["über die Rechtsprechung verfügen","鎋"],"usbekische sprache":["Usbekische Sprache","乌兹别克语"],"unbemanntes luftfahrzeug":["Unbemanntes Luftfahrzeug","无人机"],"united states army rangers":["United States Army Rangers","游骑兵"],"unsicher werden":["unsicher werden","迷惘"],"unternehmensspezifische fonds":["unternehmensspezifische Fonds","公司专用基金"],"umherstreifende und aufgelöste soldaten":["umherstreifende und aufgelöste Soldaten","散兵游勇"],"unorganisierte aktion":["unorganisierte Aktion","散兵游勇"],"unkoordinierte aktion":["unkoordinierte Aktion","散兵游勇"],"überwindbar sein":["überwindbar sein","可以克服"],"unsere zeit":["unsere Zeit","现状当代"],"unser zeitalter":["unser Zeitalter","现状当代"],"uttar pradesh":["Uttar Pradesh","北方邦"],"united press international":["United Press International","合众国际社"],"um die vorherrschaft kämpfen":["um die Vorherrschaft kämpfen","争霸"],"universität leicester":["Universität Leicester","莱斯特大学"],"unheil anrichten":["Unheil anrichten","肇事"],"university of nottingham":["University of Nottingham","诺丁汉大学"],"urbewohner von amerika":["Urbewohner von Amerika","美洲原住民"],"universität für handelsschifffahrt":["Universität für Handelsschifffahrt","海亊大学"],"über land":["über Land","经陆路"],"umsonst reden":["Umsonst reden","费口舌"],"unlauterer wettbewerb":["unlauterer Wettbewerb","不正当竞争"],"ungewöhnliches vorzeichen":["ungewöhnliches Vorzeichen","异兆"],"unter die haube kommen":["unter die Haube kommen","出嫁"],"usa today":["USA Today","今日美国"],"unten am fuß":["unten am Fuß","在脚下"],"unter dem fuß":["unter dem Fuß","在脚下"],"unterscheiden können":["unterscheiden können","识别"],"um sich blicken":["um sich blicken","转眼"],"upstate new york":["Upstate New York","纽约上州"],"unter tage":["unter Tage","井下"],"üblich sein":["üblich sein","盛行"],"united states code":["United States Code","美国法典"],"ungeklärter fall":["ungeklärter Fall","疑案"],"ungelöster fall":["ungelöster Fall","疑案"],"unnötige wiederholungen":["unnötige Wiederholungen","叠床架屋"],"unterirdisches wasser":["unterirdisches Wasser","地下水体"],"ungesättigter polyester":["ungesättigter Polyester","不饱和聚脂"],"um gottes segen bitten":["um Gottes Segen bitten","祈神赐福"],"unerlaubtes einkommen":["unerlaubtes Einkommen","非法收入"],"um frieden nachsuchen":["um Frieden nachsuchen","求和"],"unglück über unglück häufen":["Unglück über Unglück häufen","雪上加霜"],"united states air force":["United States Air Force","美国空军"],"übel mitspielen":["übel mitspielen","邋"],"über kurz oder lang":["über kurz oder lang","早晚"],"universidad de salamanca":["Universidad de Salamanca","萨拉曼卡大学"],"unparteiisch und nicht korrumpierbar":["unparteiisch und nicht korrumpierbar","铁面无私"],"übertreiben sie es nicht":["Übertreiben Sie es nicht","适可而止"],"unterhemd und unterhose":["Unterhemd und Unterhose","内衣裤"],"united center":["United Center","联合中心"],"unübersichtliche kurve":["unübersichtliche Kurve","急弯"],"ursache und wirkung":["Ursache und Wirkung","前因后果"],"überall verbreitet sein":["überall verbreitet sein","风靡"],"unerschütterlich treu bleiben":["unerschütterlich treu bleiben","忠贞不渝"],"überdachter fußweg":["überdachter Fußweg","骑楼"],"überdachter bürgersteig":["überdachter Bürgersteig","骑楼"],"unangemessene behandlung":["unangemessene Behandlung","不当治疗"],"unter gewaltandrohung erpressen":["unter Gewaltandrohung erpressen","敲诈勒索"],"unesco-welterbe europas":["UNESCO-Welterbe Europas","欧洲世界遗产"],"unter aufbietung aller kräfte":["unter Aufbietung aller Kräfte","极力"],"um dort weiterzuleben":["um dort weiterzuleben","投胎"],"untätig dahinleben":["untätig dahinleben","闲散"],"unerlaubte sexuelle beziehung":["unerlaubte sexuelle Beziehung","苟合"],"university of hong kong":["University of Hong Kong","香港大学"],"überall hinführen":["überall hinführen","四通八达"],"unter der führung":["unter der Führung","手下"],"umfang der bodenvegetation":["Umfang der Bodenvegetation","覆盖的范围"],"unscharfer druck":["unscharfer Druck","不清晰的印刷"],"übernatürliche ereignisse":["übernatürliche Ereignisse","灵异之事"],"unzählige menschen abschlachten":["unzählige Menschen abschlachten","杀人如麻"],"unmäßiges essen":["unmäßiges Essen","滥食"],"unter komplizierten bedingungen":["unter komplizierten Bedingungen","在复杂情况下"],"universität mannheim":["Universität Mannheim","曼海姆大学"],"unter rühren anbraten":["unter Rühren anbraten","焌"],"unrechtmäßig erworben":["unrechtmäßig erworben","非法获得"],"unterrichtsschluss haben":["Unterrichtsschluss haben","下课"],"unterricht beenden":["Unterricht beenden","下课"],"umar ibn al-chattab":["Umar ibn al-Chattab","奥马尔一世"],"übergeordnete behörde":["übergeordnete Behörde","上级主管机关"],"unter einsatz aller kräfte":["unter Einsatz aller Kräfte","碎裂声"],"übelriechend werden":["übelriechend werden","变臭"],"übernatürliches ereignis":["übernatürliches Ereignis","灵异事件"],"unbestechlicher beamter":["unbestechlicher Beamter","清官"],"ugedai khan":["Ugedai Khan","窝阔台"],"über etw. hinaus gehen":["über etw. hinaus gehen","跨"],"universität der künste london":["Universität der Künste London","伦敦艺术大学"],"unbefangen aussprechen":["unbefangen aussprechen","畅所欲言"],"ungesättigte fettsäure":["ungesättigte Fettsäure","不饱和脂肪酸"],"überaus schön":["überaus schön","傛"],"unregelmäßiger druck":["unregelmäßiger Druck","不平服的印刷"],"unsere familie":["unsere Familie","我们家"],"überall herumlaufen":["überall herumlaufen","奔波"],"universal coded character set":["Universal Coded Character Set","通用字符集"],"unverbunden sein":["unverbunden sein","脱节"],"unehrenhafte geschäftsleute":["unehrenhafte Geschäftsleute","不肖业者"],"unter arrest stellen":["unter Arrest stellen","押"],"unterste organisationsebene":["unterste Organisationsebene","基层"],"unabhängig davon":["unabhängig davon","无论"],"unentschlossen sein":["unentschlossen sein","举棋不定"],"unordentliches haar":["unordentliches Haar","鬃"],"ununterbrochen reden":["ununterbrochen reden","滔滔不绝"],"unbekümmertes herz":["unbekümmertes Herz","心旷神怡"],"umberto eco":["Umberto Eco","翁贝托埃科"],"uppsala län":["Uppsala län","乌普萨拉省"],"university of warwick":["University of Warwick","华威大学"],"universität montreal":["Universität Montreal","蒙特利尔大学"],"ungewöhnlicher duft":["ungewöhnlicher Duft","异香"],"umgekehrte hypothek":["umgekehrte Hypothek","倒按揭"],"universität kairo":["Universität Kairo","开罗大学"],"untere kleidung":["untere Kleidung","裳"],"university of seoul":["University of Seoul","首尔市立大学"],"ungebundener zustand":["ungebundener Zustand","游离态"],"und zwar":["und zwar","亦即"],"um ehrlich zu sein":["um ehrlich zu sein","说实在的"],"universität sorbonne":["Universität Sorbonne","索邦大学"],"unter ... umstand":["unter ... Umstand","情况下"],"unter ... umständen":["unter ... Umständen","情况下"],"unter die lupe nehmen":["unter die Lupe nehmen","观照"],"unsere präfektur etc.":["unsere Präfektur etc.","本县"],"unversöhnlicher feind":["unversöhnlicher Feind","世仇"],"unaufhörlich arbeiten":["unaufhörlich arbeiten","马不停蹄"],"überkommene regeln und gebräuche":["überkommene Regeln und Gebräuche","清规戒律"],"university of ottawa":["University of Ottawa","渥太华大学"],"unaufhörlich steigen":["unaufhörlich steigen","不断增加"],"über die befugnisse hinausgehend":["über die Befugnisse hinausgehend","超权"],"unterster akademischer grad":["unterster akademischer Grad","文学士"],"university of illinois":["University of Illinois","伊利诺大学"],"überregionale zeitung":["überregionale Zeitung","跨地区的报纸"],"university of tennessee":["University of Tennessee","田纳西大学"],"überfluss und mangel ausgleichen":["Überfluss und Mangel ausgleichen","余缺调剂"],"urspünglichen beruf":["urspünglichen Beruf","本业"],"uematsu nobuo":["Uematsu Nobuo","植松伸夫"],"über den wangen rollend":["über den Wangen rollend","簌"],"unzucht treiben":["Unzucht treiben","奸淫"],"um die ecke":["um die Ecke","在拐角处"],"unter dem ladentisch":["unter dem Ladentisch","台底交易"],"unternehmen barbarossa":["Unternehmen Barbarossa","巴巴罗萨作战"],"unnützes zeug reden":["unnützes Zeug reden","磨牙"],"über ... verhandeln":["über ... verhandeln","审理"],"unechte karettschildkröte":["Unechte Karettschildkröte","蠵龟"],"unheil stiften":["Unheil stiften","惹祸"],"u-bahn taiwan":["U-Bahn Taiwan","捷运"],"überleben des tüchtigsten":["Überleben des Tüchtigsten","适者生存"],"unsterblichkeitspillen herstellen":["Unsterblichkeitspillen herstellen","炼丹"],"unterm ladentisch geschäfte machen":["unterm Ladentisch Geschäfte machen","开后门"],"unverdientes lob":["unverdientes Lob","溢美"],"übertriebenes lob":["übertriebenes Lob","溢美"],"unter den linden":["Unter den Linden","菩提树下大街"],"unverkaufte bücher":["unverkaufte Bücher","滞销书"],"uigurische sprache":["Uigurische Sprache","维吾尔语"],"um etw. zu machen":["um etw. zu machen","抽空"],"university of manchester":["University of Manchester","曼彻斯特大学"],"unbekanntes flugzeug":["unbekanntes Flugzeug","无人飞行载具"],"universal studios":["Universal Studios","环球影业"],"undicht sein":["undicht sein","渗透"],"us-amerikanisches urheberrecht":["US-amerikanisches Urheberrecht","美国版权法"],"unsolide leben":["unsolide leben","鬼混"],"übrig geblieben":["übrig geblieben","现存"],"ungefilterte spirituosen":["ungefilterte Spirituosen","醅"],"über viele generationen":["über viele Generationen","万世"],"überall bekannt":["überall bekannt","道听途说"],"unbedruckte seite":["unbedruckte Seite","空白页"],"unerzogener ausdruck":["unerzogener Ausdruck","俗字"],"unverheiratet mit kind":["unverheiratet mit Kind","未婚先孕"],"überlegt haben":["überlegt haben","考虑过"],"um jmdn. trauern":["um jmdn. trauern","悼念"],"untere extremität":["untere Extremität","腿"],"unterstufe der mittelschule":["Unterstufe der Mittelschule","初级中学"],"über die hälfte":["über die Hälfte","大半"],"unmittelbare demokratie":["unmittelbare Demokratie","直接民主"],"unbedruckte etiketten":["unbedruckte Etiketten","空白的标签"],"über etw. tuscheln":["über etw. tuscheln","窃窃私议"],"unruhig und nervös sein":["unruhig und nervös sein","心慌意乱"],"um genau zu sein":["um genau zu sein","说得确切一些"],"university of birmingham":["University of Birmingham","伯明翰大学"],"universität uppsala":["Universität Uppsala","乌普萨拉大学"],"unechter schmuck":["unechter Schmuck","假珠宝"],"unfrieden stiften":["Unfrieden stiften","肇事"],"umm kulthum":["Umm Kulthum","邬恩考儿荪"],"unabhängig von a":["unabhängig von A","与A无关"],"über etw. lobend sprechen":["über etw. lobend sprechen","称道"],"umweltprogramm der vereinten nationen":["Umweltprogramm der Vereinten Nationen","联合国环境署"],"us regierung":["US Regierung","美国政府"],"unendliche folge":["unendliche Folge","无穷数列"],"um andere abzuschrecken":["um andere abzuschrecken","杀鸡吓猴"],"unangenehm lärmend":["unangenehm lärmend","聒"],"universität tsukuba":["Universität Tsukuba","筑波大学"],"unzensierte vetsion":["unzensierte Vetsion","完整版"],"unzensierte ausgabe":["unzensierte Ausgabe","完整版"],"umso schlimmer":["umso schlimmer","更加糟糕"],"university college london":["University College London","伦敦大学学院"],"unbelehrbare person":["unbelehrbare Person","死心眼儿"],"unruhige zeiten":["unruhige Zeiten","乱世"],"universität paris":["Universität Paris","巴黎大学"],"überteuerter preis":["überteuerter Preis","过高的价格"],"universität zürich":["Universität Zürich","苏黎世大学"],"unzufrieden mit jmdn. sein":["unzufrieden mit jmdn. sein","欿"],"unmissverständlich auf etw. hinweisen":["unmissverständlich auf etw. hinweisen","明确指出"],"unberührtes erdreich öffnen":["unberührtes Erdreich öffnen","拓荒"],"unanfechtbar sein":["unanfechtbar sein","不成立"],"unrecht gutmachen":["Unrecht gutmachen","洗寃"],"unrecht sühnen":["Unrecht sühnen","洗寃"],"um einer sache willen":["um einer Sache willen","为了"],"unter steuerung":["unter Steuerung","在控制之下"],"um die welt":["um die Welt","围绕地球"],"unabhängigkeit tibets":["Unabhängigkeit Tibets","藏独"],"unterströmender wirbel":["unterströmender Wirbel","洑"],"us-space shuttle":["US-Space Shuttle","美国太空飞机"],"united world colleges":["United World Colleges","联合世界书院"],"untadliges benehmen":["untadliges Benehmen","洁操"],"universal serial bus":["Universal Serial Bus","通用串行总线"],"university of sheffield":["University of Sheffield","谢菲尔德大学"],"urban ii.":["Urban II.","乌尔巴诺二世"],"überlebende einer schrecklichen zeit":["Überlebende einer schrecklichen Zeit","遗民"],"ununterbrochen fließen":["ununterbrochen fließen","川流不息"],"ungleichmäßige zähne":["ungleichmäßige Zähne","齱"],"unfähig gemacht":["unfähig gemacht","瘝"],"überall lauern krisen":["überall lauern Krisen","危机四优"],"unerlaubte benutzung eines fahrzeugs":["unerlaubte Benutzung eines Fahrzeugs","偷开汽车"],"universität zu köln":["Universität zu Köln","科隆大学"],"ungebleichter stoff":["ungebleichter Stoff","坯布"],"über eine grenze eindringen":["über eine Grenze eindringen","侵犯边境"],"unterirdische atomexplosion":["unterirdische Atomexplosion","地下核爆"],"überwuchert mit unkraut":["überwuchert mit Unkraut","芜"],"unsinnige überlegungen anstellen":["unsinnige Überlegungen anstellen","胡思乱想"],"überbrühte broccoli":["überbrühte Broccoli","白灼西兰花"],"überlieferte sitten":["überlieferte Sitten","传统习惯"],"universität für forstwirtschaft peking":["Universität für Forstwirtschaft Peking","北林业大学"],"umgekehrte pyramide":["umgekehrte Pyramide","倒金字塔结构"],"üppiges wachstum von bambus":["üppiges Wachstum von Bambus","篟"],"uferlose weiten":["uferlose Weiten","汪洋大海"],"utada hikaru":["Utada Hikaru","宇多田光"],"über das ufer treten":["über das Ufer treten","泛滥成灾"],"unmoralisches verhalten":["unmoralisches Verhalten","行为不道德"],"unethisches verhalten":["unethisches Verhalten","行为不道德"],"unter aller sau":["unter aller Sau","狗彘不如"],"unter jmds. kontrolle":["unter jmds. Kontrolle","掌心"],"überaus wunderlich":["überaus wunderlich","千奇百怪"],"uigurische königreich":["uigurische Königreich","高昌回鹘"],"ursula k. le guin":["Ursula K. Le Guin","娥苏拉勒瑰恩"],"university of chicago":["University of Chicago","芝加哥大学"],"unterirdische lagerstätte":["unterirdische Lagerstätte","储集层"],"unüberlegt oder gedankenlos daherreden":["unüberlegt oder gedankenlos daherreden","随口"],"unveränderliche größe":["unveränderliche Größe","无变化"],"unzufrieden und verärgert sein":["unzufrieden und verärgert sein","嗔"],"unterschiedliche behandlung":["unterschiedliche Behandlung","差别待遇"],"über etw. entscheiden":["über etw. entscheiden","做主"],"umändern in":["umändern in","改到"],"unterkunft für gäste":["Unterkunft für Gäste","馆"],"unsicherer gang":["unsicherer Gang","蹒跚学步"],"umfassende qualitätskontrolle":["umfassende Qualitätskontrolle","总体质量控制"],"universität rostock":["Universität Rostock","罗斯托克大学"],"unter verweis auf":["unter Verweis auf","参照"],"university of maine":["University of Maine","缅因大学"],"über eine brücke gehen":["über eine Brücke gehen","过桥"],"university of western ontario":["University of Western Ontario","西安大略大学"],"unmäßiges trinken":["unmäßiges Trinken","纵酒"],"über etw. herrschen":["über etw. herrschen","宰"],"uma thurman":["Uma Thurman","乌玛瑟曼"],"universität paderborn":["Universität Paderborn","帕德博恩大学"],"unzufrieden erscheinen":["unzufrieden erscheinen","媁"],"untere tunguska":["Untere Tunguska","下通古斯河"],"um spenden bitten":["um Spenden bitten","募捐"],"urban i.":["Urban I.","乌尔巴诺一世"],"über der norm":["über der Norm","规模以上"],"um andere zu retten":["um andere zu retten","舍身救人"],"unsterblicher dichter":["unsterblicher Dichter","诗仙"],"um ein haar":["um ein Haar","险些儿"],"universität halle":["Universität Halle","哈雷大学"],"uni air":["Uni Air","立荣航空"],"uneingeschränkte freiheit erlauben":["uneingeschränkte Freiheit erlauben","放任自由"],"unter druck":["unter Druck","在压力下"],"unverrichteter dinge zurückkehren":["unverrichteter Dinge zurückkehren","空手而归"],"unüberlegt nachplappern":["unüberlegt nachplappern","拾人牙慧"]}